noise.py
circuitpython_noise-1.0.2.dist-info/LICENSE
circuitpython_noise-1.0.2.dist-info/METADATA
circuitpython_noise-1.0.2.dist-info/WHEEL
circuitpython_noise-1.0.2.dist-info/top_level.txt
circuitpython_noise-1.0.2.dist-info/RECORD
