Metadata-Version: 2.1
Name: circuitpython-noise
Version: 1.0.2
Summary: Simplex noise (like Perlin) for CircuitPython
Author-email: Adafruit Industries <circuitpython@adafruit.com>
License: MIT
Project-URL: Homepage, https://github.com/todbot/CircuitPython_Noise
Keywords: adafruit,blinka,circuitpython,micropython,noise,noise,simplex,perlin,gradient
Classifier: Intended Audience :: Developers
Classifier: Topic :: Software Development :: Libraries
Classifier: Topic :: Software Development :: Embedded Systems
Classifier: Topic :: System :: Hardware
Classifier: License :: OSI Approved :: MIT License
Classifier: Programming Language :: Python :: 3
License-File: LICENSE
Requires-Dist: Adafruit-Blinka
Provides-Extra: optional
